cogkge/__init__.py
cogkge/adapter/__init__.py
cogkge/adapter/description_adapter.py
cogkge/adapter/graph_adapter.py
cogkge/adapter/time_adapter.py
cogkge/adapter/type_adapter.py
cogkge/core/__init__.py
cogkge/core/dataloader.py
cogkge/core/evaluator.py
cogkge/core/log.py
cogkge/core/loss.py
cogkge/core/metric.py
cogkge/core/predictor.py
cogkge/core/sampler.py
cogkge/core/trainer.py
cogkge/data/__init__.py
cogkge/data/datable.py
cogkge/data/dataset.py
cogkge/data/lut.py
cogkge/data/vocabulary.py
cogkge/data/loader/__init__.py
cogkge/data/loader/baseloader.py
cogkge/data/loader/codexlloader.py
cogkge/data/loader/codexmloader.py
cogkge/data/loader/codexsloader.py
cogkge/data/loader/cognet360kloader.py
cogkge/data/loader/cskgloader.py
cogkge/data/loader/eventkg240kloader.py
cogkge/data/loader/fb15k237loader.py
cogkge/data/loader/fb15kloader.py
cogkge/data/loader/mobilewikidata5mloader.py
cogkge/data/loader/wikidata5mloader.py
cogkge/data/loader/wikipedia5mloader.py
cogkge/data/loader/wn18loader.py
cogkge/data/loader/wn18rrloader.py
cogkge/data/processor/__init__.py
cogkge/data/processor/baseprocessor.py
cogkge/data/processor/codexlprocessor.py
cogkge/data/processor/codexmprocessor.py
cogkge/data/processor/codexsprocessor.py
cogkge/data/processor/cognet360kprocessor.py
cogkge/data/processor/cskgprocessor.py
cogkge/data/processor/eventkg240kprocessor.py
cogkge/data/processor/fb15k237processor.py
cogkge/data/processor/fb15kprocessor.py
cogkge/data/processor/mobilewikidata5mprocessor.py
cogkge/data/processor/wikidata5mprocessor.py
cogkge/data/processor/wikipedia5mprocessor.py
cogkge/data/processor/wn18processor.py
cogkge/data/processor/wn18rrprocessor.py
cogkge/models/__init__.py
cogkge/models/basemodel.py
cogkge/models/boxe.py
cogkge/models/compgcn.py
cogkge/models/complex.py
cogkge/models/distmult.py
cogkge/models/hitter.py
cogkge/models/kepler.py
cogkge/models/pairre.py
cogkge/models/rescal.py
cogkge/models/rgcn.py
cogkge/models/rotate.py
cogkge/models/simple.py
cogkge-0.2.0.dist-info/LICENSE
cogkge-0.2.0.dist-info/METADATA
cogkge-0.2.0.dist-info/WHEEL
cogkge-0.2.0.dist-info/top_level.txt
cogkge-0.2.0.dist-info/RECORD
