Metadata-Version: 2.1
Name: cogkge
Version: 0.2.0
Summary: CogKGE: A Knowledge Graph Embedding Toolkit and Benckmark for Representing Multi-source and Heterogeneous Knowledge
Home-page: https://github.com/jinzhuoran/CogKGE/
Author: CogNLP Team
Author-email: zhuoran.jin@nlpr.ia.ac.cn
License: MIT
Requires-Python: >=3.7,<3.9
License-File: LICENSE
Requires-Dist: torch (>=1.10.0)
Requires-Dist: pandas (>=1.3.3)
Requires-Dist: openTSNE (>=0.6.1)
Requires-Dist: transformers (>=4.4.2)
Requires-Dist: matplotlib (>=3.4.3)
Requires-Dist: prefetch-generator (>=1.0.1)
Requires-Dist: prettytable (>=2.4.0)
Requires-Dist: tensorboard (>=2.7.0)
Requires-Dist: tqdm (>=4.62.3)
Requires-Dist: nltk (>=3.5)
Requires-Dist: PyYAML (>=5.4.1)
Requires-Dist: mongoengine (>=0.23.1)
